mltu/__init__.py
mltu/augmentors.py
mltu/configs.py
mltu/dataProvider.py
mltu/inferenceModel.py
mltu/preprocessors.py
mltu/tokenizers.py
mltu/transformers.py
mltu/annotations/__init__.py
mltu/annotations/audio.py
mltu/annotations/detections.py
mltu/annotations/images.py
mltu/tensorflow/__init__.py
mltu/tensorflow/callbacks.py
mltu/tensorflow/dataProvider.py
mltu/tensorflow/layers.py
mltu/tensorflow/losses.py
mltu/tensorflow/metrics.py
mltu/tensorflow/model_utils.py
mltu/tensorflow/transformer/__init__.py
mltu/tensorflow/transformer/attention.py
mltu/tensorflow/transformer/callbacks.py
mltu/tensorflow/transformer/layers.py
mltu/tensorflow/transformer/utils.py
mltu/torch/__init__.py
mltu/torch/callbacks.py
mltu/torch/dataProvider.py
mltu/torch/handlers.py
mltu/torch/losses.py
mltu/torch/metrics.py
mltu/torch/model.py
mltu/torch/yolo/__init__.py
mltu/torch/yolo/annotation.py
mltu/torch/yolo/loss.py
mltu/torch/yolo/metrics.py
mltu/torch/yolo/optimizer.py
mltu/torch/yolo/preprocessors.py
mltu/torch/yolo/pruning_utils.py
mltu/torch/yolo/detectors/__init__.py
mltu/torch/yolo/detectors/detector.py
mltu/torch/yolo/detectors/onnx_detector.py
mltu/torch/yolo/detectors/torch_detector.py
mltu/utils/__init__.py
mltu/utils/text_utils.py
mltu-1.2.5.dist-info/LICENSE
mltu-1.2.5.dist-info/METADATA
mltu-1.2.5.dist-info/WHEEL
mltu-1.2.5.dist-info/top_level.txt
mltu-1.2.5.dist-info/RECORD
