Metadata-Version: 2.1
Name: mltu
Version: 1.2.5
Summary: Machine Learning Training Utilities (MLTU) for TensorFlow and PyTorch
Home-page: https://pylessons.com/
Author: PyLessons
Author-email: pythonlessons0@gmail.com
Project-URL: Source, https://github.com/pythonlessons/mltu/
Project-URL: Tracker, https://github.com/pythonlessons/mltu/issues
Requires-Python: >=3
License-File: LICENSE
Requires-Dist: PyYAML >=6.0
Requires-Dist: tqdm
Requires-Dist: qqdm ==0.0.7
Requires-Dist: pandas
Requires-Dist: numpy
Requires-Dist: opencv-python
Requires-Dist: Pillow >=9.4.0
Requires-Dist: onnxruntime >=1.15.0
Requires-Dist: matplotlib
Provides-Extra: gpu
Requires-Dist: onnxruntime-gpu ; extra == 'gpu'
